{
  "$schema": "http://json.schemastore.org/template",
  "author": "Nice3point",
  "name": "Revit Test (TUnit)",
  "shortName": "revit-tunit",
  "identity": "Nice3point.TUnit.Revit",
  "defaultName": "RevitTests",
  "sourceName": "Nice3point.Unit.Revit",
  "description": "Template for creating unit tests for Revit API",
  "classifications": [
    "Revit",
    "Unit",
    "Test",
    "API",
    "TUnit"
  ],
  "tags": {
    "type": "project",
    "language": "C#",
    "platform": ".NET"
  },
  "preferNameDirectory": true
}